<?xml-model href="../../greatcomet_schema.rnc" type="application/relax-ng-compact-syntax"?>
<song title="Sonya Alone"><metadata>
    <name>Sonya Alone</name>
    <characters>
        <c>SONYA</c>
    </characters>
    <source>https://genius.com/Dave-malloy-sonya-alone-lyrics</source>
</metadata>
<lyrics>
    <verse>
        <stanza speaker="SONYA">
           <wp-ref id="wp-ref116"><line>Hard as it is</line>
            <line>In the coming days</line>
            <line>I watch <chara ref="NATASHA">my friend</chara></line>
            <line>In her strange unnatural state</line>
            <line>Don’t let her out of my sight</line>
            <s-action descr="NATASHA" kind="other"><line>She trails off</line>
            <line>Stares at nothing</line>
            <line>Laughs at random</line></s-action></wp-ref>
            <line>And the letters come</line>
            <s-action kind="other" descr="NATASHA"><line>She waits by the window</line></s-action>
            <wp-ref id="wp-ref117"><s-action kind="self" descr="SONYA" type="1st"><line>And I listen at the door</line></s-action></wp-ref>
            <line>Until one day</line>
            <line>I see by the sad look on her face</line>
            <wp-ref id="wp-ref117"><line>There is a dreadful plan in her heart</line></wp-ref>
        </stanza>

        <stanza speaker="SONYA">
            <line>I know you are capable of anything</line>
            <line>I know you so well <chara ref="NATASHA">my friend</chara></line>
            <wp-ref id="wp-ref118"><line>I know you might just run away</line>
            <line>What am I to do?</line>
            <line>Who do I ask for help?</line></wp-ref>
            <line>Is it all on me?</line>
            <line>Is it all on me?</line>
        </stanza>
    </verse>

    <chorus>
        <stanza speaker="SONYA">
            <wp-ref id="wp-ref118"><line>I will stand in the dark for you</line>
            <line>I will hold you back by force</line>
            <line>I will stand here right outside your door</line>
            <line>I won’t see you disgraced</line>
            <line>I will protect your name and your heart</line></wp-ref>
            <line>Because I miss <chara ref="NATASHA">my friend</chara></line>
        </stanza>
    </chorus>

    <verse>
        <stanza speaker="SONYA">
            <line>I know you’ve forgotten me</line>
            <line>I know you so well <chara ref="NATASHA">my friend</chara></line>
            <line>I know you might just throw yourself over</line>
            <line>But I won’t let you</line>
            <line>I won’t let you</line>
            <line>It’s all on me</line>
        </stanza>

        <stanza speaker="SONYA">
            <wp-ref id="wp-ref118"><line>And I remember this family</line>
            <line>I remember their kindness</line>
            <line>And if I never sleep again</line></wp-ref>
        </stanza>
    </verse>

    <chorus>
        <stanza speaker="SONYA">
            <wp-ref id="wp-ref118"><line>I will stand in the dark for you</line>
            <line>I will hold you back by force</line>
            <line>I will stand here right outside your door</line>
            <line>I won’t see you disgraced</line>
            <line>I will protect your name and your heart</line></wp-ref>
            <line>Because I miss <chara ref="NATASHA">my friend</chara></line>
            <line>Because I miss <chara ref="NATASHA">my friend</chara></line>
            <line>Because I miss you, <chara ref="NATASHA">my friend</chara></line>
        </stanza>
    </chorus>
</lyrics>
</song>